mindbox/__init__.py
mindbox/activation_layer.py
mindbox/activations.py
mindbox/console.py
mindbox/core.py
mindbox/fully_connected_layer.py
mindbox/layer.py
mindbox/losses.py
mindbox/network.py
mindbox/usage.py
mindbox-0.1.1.dist-info/LICENSE
mindbox-0.1.1.dist-info/METADATA
mindbox-0.1.1.dist-info/WHEEL
mindbox-0.1.1.dist-info/top_level.txt
mindbox-0.1.1.dist-info/RECORD
